jitcdde/__init__.py
jitcdde/_jitcdde.py
jitcdde/_python_core.py
jitcdde/jitced_template.c
jitcdde/past.py
jitcdde/sympy_symbols.py
jitcdde/version.py
jitcdde-1.8.3.dist-info/licenses/LICENSE
jitcdde-1.8.3.dist-info/METADATA
jitcdde-1.8.3.dist-info/WHEEL
jitcdde-1.8.3.dist-info/top_level.txt
jitcdde-1.8.3.dist-info/RECORD
